knot/__init__.py
knot/bus.py
knot/factory.py
knot/plugins/celery/__init__.py
knot/plugins/celery/bus.py
knot/plugins/celery/queue/__init__.py
knot/plugins/celery/queue/module_path.py
knot/plugins/celery/queue/queue_task.py
knot/plugins/di/__init__.py
knot/plugins/di/provider.py
knot/types/__init__.py
knot/types/handler.py
knot/types/message.py
pyknot-1.0.0.dist-info/METADATA
pyknot-1.0.0.dist-info/WHEEL
pyknot-1.0.0.dist-info/RECORD
