Metadata-Version: 2.1
Name: pyknot
Version: 1.0.0
Summary: A Python-based message bus system designed for message handling and crafted to integrate with dependency injection frameworks.
Author: Retr0327
Author-email: retr0327.dev@gmail.com
Requires-Python: >=3.10,<4.0
Classifier: Programming Language :: Python :: 3
Classifier: Programming Language :: Python :: 3.10
Classifier: Programming Language :: Python :: 3.11
Requires-Dist: celery (>=5.3.5,<6.0.0)
Requires-Dist: dependency-injector (>=4.41.0,<5.0.0)
